2018 Image Display Control/LCD_CTRL.v
module LCD_CTRL(clk, reset, cmd, cmd_valid, IROM_Q, IROM_rd, IROM_A, IRAM_valid, IRAM_D, IRAM_A, busy, done);
input           clk;
input           reset;
input [3:0]     cmd;        // command
input           cmd_valid;  // is command enable
input [7:0]     IROM_Q;     // ROM data
// -------------------------------------------------------
output reg           IROM_rd;    // ROM data read enable
output reg  [5:0]    IROM_A;     // ROM Address
output reg           IRAM_valid;
output reg  [7:0]    IRAM_D;
output reg  [5:0]    IRAM_A;
output reg           busy;
output reg           done;

parameter   FetchStage   = 2'd0,
            IdleStage    = 2'd1,
            CommandStage = 2'd2,
            WriteStage   = 2'd3;

parameter   WriteCmd        = 4'h0,
            ShiftUpCmd      = 4'h1,
            ShiftDownCmd    = 4'h2,
            ShiftLeftCmd    = 4'h3,
            ShiftRightCmd   = 4'h4,
            MaxCmd          = 4'h5,
            MinCmd          = 4'h6,
            AverageCmd      = 4'h7,
            CCWRotateCmd    = 4'h8,
            CWRotateCmd     = 4'h9,
            MirrorXCmd      = 4'hA,
            MirrorYCmd      = 4'hB;

reg [7:0]   RAM [63:0];
reg [1:0]   state;
reg [1:0]   next_state;

/* 
===========================================================================================================
// Finite State Machine
===========================================================================================================
*/
always @(posedge clk or posedge reset) begin
    if (reset) 
        state <= FetchStage;
    else 
        state <= next_state;
end
always @(*) begin
    if (state == FetchStage) begin
        next_state = (IROM_A == 6'd63) ? IdleStage : FetchStage;
    end
    else if (state == IdleStage) begin
        if (cmd_valid && cmd == WriteCmd) 
            next_state = WriteStage;
        else if (cmd_valid) 
            next_state = CommandStage;
        else 
            next_state = IdleStage;
    end
    else if (state == CommandStage) begin
        next_state = IdleStage;
    end
    else if (state == WriteStage) begin
        next_state = WriteStage;
    end
    else begin
        next_state = next_state;
    end
end
/*
===========================================================================================================
Control Unit
===========================================================================================================
*/
always @(*) begin
    if (reset) begin
        busy <= 1'b1;
        done <= 1'b0;
        IRAM_valid <= 1'b0;
    end
    else if (state == FetchStage) begin
        busy <= 1'b1;
        done <= 1'b0;
        IRAM_valid <= 1'b0;
    end
    else if (state == IdleStage) begin
        busy <= 1'b0;
        done <= 1'b0;
        IRAM_valid <= 1'b0;
    end
    else if (state == CommandStage) begin
        busy <= 1'b1;
        done <= 1'b0;
        IRAM_valid <= 1'b0;
    end
    else if (state == WriteStage) begin
        busy <= 1'b1;
        IRAM_valid <= 1'b1;
    end
    else begin
        
    end
end

always @(posedge clk) begin
    if (state == IdleStage) begin
        if (cmd == WriteCmd) $display("Command Name: WriteCmd");
        else if (cmd == ShiftUpCmd) $display("Command Name: ShiftUpCmd");
        else if (cmd == ShiftDownCmd) $display("Command Name: ShiftDownCmd");
        else if (cmd == ShiftLeftCmd) $display("Command Name: ShiftLeftCmd");
        else if (cmd == ShiftRightCmd) $display("Command Name: ShiftRightCmd");
        else if (cmd == MaxCmd) $display("Command Name: MaxCmd");
        else if (cmd == MinCmd) $display("Command Name: MinCmd");
        else if (cmd == AverageCmd) $display("Command Name: AverageCmd");
        else if (cmd == CCWRotateCmd) $display("Command Name: CCWRotateCmd");
        else if (cmd == CWRotateCmd) $display("Command Name: CWRotateCmd");
        else if (cmd == MirrorXCmd) $display("Command Name: MirrorXCmd");
        else if (cmd == MirrorYCmd) $display("Command Name: MirrorYCmd");
        else $display("No Command");
    end
    else begin
        
    end
end

/*      
===========================================================================================================
Fetch From ROM:
1. ROM address ++
2. Fetch Data: ROM -> RAM
=========================================================================================================== 
*/
always @(posedge clk or posedge reset) begin
    if (reset) begin
        IROM_A <= 0;
    end
    else if (state == FetchStage) begin
        IROM_A <= (IROM_A == 6'd63) ? IROM_A : IROM_A + 6'd1;
    end
    else begin
        IROM_A <= IROM_A;
    end
end
always @(posedge clk or posedge reset) begin
    if (reset) begin
        IROM_rd <= 1'b1;
    end
    else if (state == FetchStage) begin
        RAM[IROM_A] <= IROM_Q;
        IROM_rd <= 1'b1;
    end
    else begin
        RAM[IROM_A] <= RAM[IROM_A];
        IROM_rd <= 1'b0;
    end
end

/*      
===========================================================================================================
Get Command
1. Operation Point starts at (4,4) -> 36, but (3,3) -> 28 is the real starting point 
2. Shift may out of bound
3. Addition for average may overflow 
===========================================================================================================
*/
reg [5:0] OpIdx;
wire [5:0] OpIdx1, OpIdx2, OpIdx3;
assign OpIdx1 = OpIdx + 6'd1;
assign OpIdx2 = OpIdx + 6'd8;
assign OpIdx3 = OpIdx + 6'd9;

reg [7:0] peep0, peep1, peep2, peep3;

always @(posedge clk or posedge reset) begin
    if (reset) begin
        OpIdx <= 6'h1B;
        peep0 <= 0;
        peep1 <= 0;
        peep2 <= 0;
        peep3 <= 0;
    end
    else if (CommandStage && busy) begin
        case (cmd)
            ShiftUpCmd: 
                OpIdx[5:3] <= (OpIdx[5:3] == 3'd0) ? OpIdx[5:3] : OpIdx[5:3] - 3'd1;
            ShiftDownCmd: 
                OpIdx[5:3] <= (OpIdx[5:3] == 3'd6) ? OpIdx[5:3] : OpIdx[5:3] + 3'd1;
            ShiftLeftCmd: 
                OpIdx[2:0] <= (OpIdx[2:0] == 3'd0) ? OpIdx[2:0] : OpIdx[2:0] - 3'd1;
            ShiftRightCmd: 
                OpIdx[2:0] <= (OpIdx[2:0] == 3'd6) ? OpIdx[2:0] : OpIdx[2:0] + 3'd1;
            MaxCmd: begin
                RAM[OpIdx] <= RAM[max_idx];
                RAM[OpIdx1] <= RAM[max_idx];
                RAM[OpIdx2] <= RAM[max_idx];
                RAM[OpIdx3] <= RAM[max_idx];
            end
            MinCmd: begin
                RAM[OpIdx] <= RAM[min_idx];
                RAM[OpIdx1] <= RAM[min_idx];
                RAM[OpIdx2] <= RAM[min_idx];
                RAM[OpIdx3] <= RAM[min_idx];
            end
            AverageCmd: begin
                RAM[OpIdx] <= sum_val[9:2];
                RAM[OpIdx1] <= sum_val[9:2];
                RAM[OpIdx2] <= sum_val[9:2];
                RAM[OpIdx3] <= sum_val[9:2];
            end
            CWRotateCmd: begin
                RAM[OpIdx] <= RAM[OpIdx2];
                RAM[OpIdx1] <= RAM[OpIdx];
                RAM[OpIdx2] <= RAM[OpIdx3];
                RAM[OpIdx3] <= RAM[OpIdx1];
            end
            CCWRotateCmd: begin
                RAM[OpIdx] <= RAM[OpIdx1];
                RAM[OpIdx1] <= RAM[OpIdx3];
                RAM[OpIdx2] <= RAM[OpIdx];
                RAM[OpIdx3] <= RAM[OpIdx2];
            end
            MirrorXCmd: begin
                RAM[OpIdx] <= RAM[OpIdx2];
                RAM[OpIdx1] <= RAM[OpIdx3];
                RAM[OpIdx2] <= RAM[OpIdx];
                RAM[OpIdx3] <= RAM[OpIdx1];
            end
            MirrorYCmd: begin
                RAM[OpIdx] <= RAM[OpIdx1];
                RAM[OpIdx1] <= RAM[OpIdx];
                RAM[OpIdx2] <= RAM[OpIdx3];
                RAM[OpIdx3] <= RAM[OpIdx2];
            end
            default: begin
                OpIdx <= OpIdx;
            end
        endcase
        peep0 <= RAM[OpIdx];
        peep1 <= RAM[OpIdx1];
        peep2 <= RAM[OpIdx2];
        peep3 <= RAM[OpIdx3];
    end
    else begin
        
    end
end

/* Comparison */
reg [5:0] min_idx, max_idx;
wire [9:0] sum_val;
assign sum_val = (RAM[OpIdx] + RAM[OpIdx1] + RAM[OpIdx2] + RAM[OpIdx3]);
always @(*) begin
    if (RAM[OpIdx] >= RAM[OpIdx1] && RAM[OpIdx] >= RAM[OpIdx2] && RAM[OpIdx] >= RAM[OpIdx3])
        max_idx = OpIdx;
    else if (RAM[OpIdx1] >= RAM[OpIdx] && RAM[OpIdx1] >= RAM[OpIdx2] && RAM[OpIdx1] >= RAM[OpIdx3])
        max_idx = OpIdx1;
    else if (RAM[OpIdx2] >= RAM[OpIdx] && RAM[OpIdx2] >= RAM[OpIdx1] && RAM[OpIdx2] >= RAM[OpIdx3])
        max_idx = OpIdx2;
    else
        max_idx = OpIdx3;
end
always @(*) begin
    if (RAM[OpIdx] <= RAM[OpIdx1] && RAM[OpIdx] <= RAM[OpIdx2] && RAM[OpIdx] <= RAM[OpIdx3])
        min_idx = OpIdx;
    else if (RAM[OpIdx1] <= RAM[OpIdx] && RAM[OpIdx1] <= RAM[OpIdx2] && RAM[OpIdx1] <= RAM[OpIdx3])
        min_idx = OpIdx1;
    else if (RAM[OpIdx2] <= RAM[OpIdx] && RAM[OpIdx2] <= RAM[OpIdx1] && RAM[OpIdx2] <= RAM[OpIdx3])
        min_idx = OpIdx2;
    else
        min_idx = OpIdx3;
end

/*
===========================================================================================================
Write Back to RAM: check the timing 
===========================================================================================================
*/
reg [5:0] nx_idx;
always @(posedge clk or posedge reset) begin
    if (reset) begin 
        nx_idx <= 6'd0;
    end
    else if ((state == WriteStage && nx_idx < 6'd63)) begin
        nx_idx <= nx_idx + 6'd1;
    end
    else if ((state == WriteStage && nx_idx == 6'd63)) begin
        nx_idx <= 6'd63;
    end
end
always @(posedge clk or posedge reset) begin
    if (reset) begin 
        IRAM_A <= 6'd0;
    end
    else if ((state == WriteStage && IRAM_A < 6'd63)) begin
        IRAM_A <= nx_idx;
    end
    else if ((state == WriteStage && IRAM_A == 6'd63)) begin
        IRAM_A <= 6'd63;
        done <= 1'b1;
    end
end
always @(posedge clk or posedge reset) begin
    if (reset) begin 
        IRAM_D <= 8'd0;
    end
    else if (state == WriteStage) begin
        IRAM_D <= RAM[nx_idx];
    end
end



endmodule

2018 Image Display Control/testfixture.v
`timescale 1ns/10ps
`define CYCLE    10.0         	        // Modify your clock period here


`define SDFFILE  "./LCD_CTRL_syn.sdf"	// Modify your sdf file name

`ifdef tb1
  `define EXPECT "./tb1_goal.dat"
  `define CMD "./cmd1.dat"
  `define IMAGE "image1.dat"
`endif

`ifdef tb2
  `define EXPECT "./tb2_goal.dat"
  `define CMD "./cmd2.dat"
  `define IMAGE "image2.dat"
`endif

`ifdef tb3
  `define EXPECT "./tb3_goal.dat"
  `define CMD "./cmd3.dat"
  `define IMAGE "image3.dat"
`endif


module test;
parameter IMAGE_N_PAT = 64;
parameter CMD_N_PAT = 46;
parameter t_reset = `CYCLE*2;


reg clk;
reg reset;
reg [6:0] err_IRAM;
reg [3:0] cmd;
reg cmd_valid;
reg [7:0]  out_mem[0:63];


wire IROM_rd;
wire [5:0] IROM_A;
wire IRAM_valid;
wire [7:0] IRAM_D;
wire [5:0] IRAM_A;
wire busy;
wire done;
wire [7:0]  IROM_Q;


integer i, j, k, l, err;

reg		over;
reg   [3:0]   cmd_mem   [0:CMD_N_PAT-1];



LCD_CTRL LCD_CTRL(
	.clk(clk), .reset(reset), 
	.cmd(cmd), .cmd_valid(cmd_valid), 
    .IROM_rd(IROM_rd), .IROM_A(IROM_A), .IROM_Q(IROM_Q), 
    .IRAM_valid(IRAM_valid), .IRAM_D(IRAM_D), .IRAM_A(IRAM_A),
	.busy(busy), .done(done)
);

IROM  IROM_1(
	.IROM_rd(IROM_rd), .IROM_data(IROM_Q), 
	.IROM_addr(IROM_A), .clk(clk), .reset(reset)
);

IRAM IRAM_1 (
	.clk(clk), .IRAM_data(IRAM_D), 
	.IRAM_addr(IRAM_A), .IRAM_valid(IRAM_valid)
);


// initial $sdf_annotate(`SDFFILE, top);

`ifdef SDF
	initial $sdf_annotate(`SDFFILE, LCD_CTRL);
`endif

initial	$readmemh (`CMD,    cmd_mem);
initial	$readmemh (`EXPECT, out_mem);

// initial begin

// $fsdbDumpfile("LCD_CTRL.fsdb");
// $fsdbDumpvars;
// $fsdbDumpMDA;
// end

initial begin
    // Open a VCD file for dumping waveform data
    $dumpfile("LCD_CTRL.vcd");
    $dumpvars(0, test);
end

initial begin
   clk         = 1'b0;
   reset       = 1'b0;
   over	       = 1'b0;
   l	       = 0;
   err         = 0;   
end

always begin #(`CYCLE/2) clk = ~clk; end

initial begin
   @(negedge clk)  reset = 1'b1;
   #t_reset        reset = 1'b0;
                                  
end  

reg [9:0] cnt;
always @(posedge clk or posedge reset) begin
	if (reset) cnt <= 0;
	else if (cnt == 10'd1000) $finish;
	else cnt <= cnt + 1;
end

            
always @(negedge clk)
begin
	if (l < CMD_N_PAT) begin
		if(!busy) begin
        	cmd = cmd_mem[l];
        	cmd_valid = 1'b1;
			l=l+1;
		end  
		else
			cmd_valid = 1'b0;
	end
	else begin
		l=l;
		cmd_valid = 1'b0;
	end
end


initial @(posedge done) 
begin
   	for(k=0;k<64;k=k+1)begin
        if( IRAM_1.IRAM_M[k] !== out_mem[k]) begin
         	$display("ERROR at %d:output %h !=expect %h ",k, IRAM_1.IRAM_M[k], out_mem[k]);
         	err = err+1 ;
		end
        else if ( out_mem[k] === 8'dx) begin
            $display("ERROR at %d:output %h !=expect %h ",k, IRAM_1.IRAM_M[k], out_mem[k]);
			err=err+1;
        end   
 		over=1'b1;
	end
    begin
		if (err === 0 &&  over===1'b1  )  begin
			$display("All data have been generated successfully!\n");
			$display("-------------------PASS-------------------\n");
			#10 $finish;
		end
		else if( over===1'b1 )
		begin 
			$display("There are %d errors!\n", err);
			$display("---------------------------------------------\n");
			#10 $finish;
		end
	end
end

endmodule


//-----------------------------------------------------------------------
//-----------------------------------------------------------------------
module IROM (IROM_rd, IROM_data, IROM_addr, clk, reset);
input		IROM_rd;
input	[5:0] 	IROM_addr;
output	[7:0]	IROM_data;
input		clk, reset;

reg [7:0] sti_M [0:63];
integer i;

reg	[7:0]	IROM_data;

initial begin
	@ (negedge reset) $readmemb (`IMAGE , sti_M);
end

always@(negedge clk) 
	if (IROM_rd) IROM_data <= sti_M[IROM_addr];
	
endmodule



//-----------------------------------------------------------------------
//-----------------------------------------------------------------------

module IRAM (IRAM_valid, IRAM_data, IRAM_addr, clk);
input		IRAM_valid;
input	[5:0] 	IRAM_addr;
input	[7:0]	IRAM_data;
input		clk;

reg [7:0] IRAM_M [0:63];
integer i;

initial begin
	for (i=0; i<=63; i=i+1) IRAM_M[i] = 0; 
end

always@(negedge clk) 
	if (IRAM_valid) IRAM_M[ IRAM_addr ] <= IRAM_data;

endmodule

2018 Image Display Control/LCD_CTRL.vcd
$date
	Sun Feb 16 23:13:48 2025
$end
$version
	Icarus Verilog
$end
$timescale
	10ps
$end
$scope module test $end
$var wire 1 ! done $end
$var wire 1 " busy $end
$var wire 1 # IROM_rd $end
$var wire 8 $ IROM_Q [7:0] $end
$var wire 6 % IROM_A [5:0] $end
$var wire 1 & IRAM_valid $end
$var wire 8 ' IRAM_D [7:0] $end
$var wire 6 ( IRAM_A [5:0] $end
$var reg 1 ) clk $end
$var reg 4 * cmd [3:0] $end
$var reg 1 + cmd_valid $end
$var reg 10 , cnt [9:0] $end
$var reg 1 - over $end
$var reg 1 . reset $end
$var integer 32 / err [31:0] $end
$var integer 32 0 k [31:0] $end
$var integer 32 1 l [31:0] $end
$scope module IRAM_1 $end
$var wire 1 ) clk $end
$var wire 1 & IRAM_valid $end
$var wire 8 2 IRAM_data [7:0] $end
$var wire 6 3 IRAM_addr [5:0] $end
$var integer 32 4 i [31:0] $end
$upscope $end
$scope module IROM_1 $end
$var wire 1 ) clk $end
$var wire 1 . reset $end
$var wire 1 # IROM_rd $end
$var wire 6 5 IROM_addr [5:0] $end
$var reg 8 6 IROM_data [7:0] $end
$upscope $end
$scope module LCD_CTRL $end
$var wire 8 7 IROM_Q [7:0] $end
$var wire 1 ) clk $end
$var wire 4 8 cmd [3:0] $end
$var wire 1 + cmd_valid $end
$var wire 1 . reset $end
$var wire 10 9 sum_val [9:0] $end
$var wire 6 : OpIdx3 [5:0] $end
$var wire 6 ; OpIdx2 [5:0] $end
$var wire 6 < OpIdx1 [5:0] $end
$var reg 6 = IRAM_A [5:0] $end
$var reg 8 > IRAM_D [7:0] $end
$var reg 1 & IRAM_valid $end
$var reg 6 ? IROM_A [5:0] $end
$var reg 1 # IROM_rd $end
$var reg 6 @ OpIdx [5:0] $end
$var reg 1 " busy $end
$var reg 1 ! done $end
$var reg 6 A max_idx [5:0] $end
$var reg 6 B min_idx [5:0] $end
$var reg 2 C next_state [1:0] $end
$var reg 6 D nx_idx [5:0] $end
$var reg 8 E peep0 [7:0] $end
$var reg 8 F peep1 [7:0] $end
$var reg 8 G peep2 [7:0] $end
$var reg 8 H peep3 [7:0] $end
$var reg 2 I state [1:0] $end
$upscope $end
$upscope $end
$enddefinitions $end
#0
$dumpvars
bx I
bx H
bx G
bx F
bx E
bx D
bx C
bx B
bx A
bx @
bx ?
bx >
bx =
bx <
bx ;
bx :
bx 9
bx 8
bx 7
bx 6
bx 5
b1000000 4
bx 3
bx 2
b0 1
bx 0
b0 /
0.
0-
bx ,
x+
bx *
0)
bx (
bx '
x&
bx %
bx $
x#
x"
x!
$end
#500
0#
1)
#1000
b100100 B
b100100 A
b0 C
b0 ,
b0 '
b0 2
b0 >
b0 (
b0 3
b0 =
b0 D
b0 H
b0 G
b0 F
b0 E
b11100 <
b100011 ;
b100100 :
b11011 @
1#
b0 %
b0 5
b0 ?
b0 I
0&
0!
1"
1.
0+
0)
#1500
1)
#2000
b0 $
b0 6
b0 7
0)
#2500
1)
#3000
0)
0.
#3500
b1 %
b1 5
b1 ?
bx H
bx G
bx F
bx E
b1 ,
1)
#4000
b1 $
b1 6
b1 7
0)
#4500
b10 ,
b10 %
b10 5
b10 ?
1)
#5000
b10 $
b10 6
b10 7
0)
#5500
b11 %
b11 5
b11 ?
b11 ,
1)
#6000
b11 $
b11 6
b11 7
0)
#6500
b100 ,
b100 %
b100 5
b100 ?
1)
#7000
b100 $
b100 6
b100 7
0)
#7500
b101 %
b101 5
b101 ?
b101 ,
1)
#8000
b101 $
b101 6
b101 7
0)
#8500
b110 ,
b110 %
b110 5
b110 ?
1)
#9000
b110 $
b110 6
b110 7
0)
#9500
b111 %
b111 5
b111 ?
b111 ,
1)
#10000
b111 $
b111 6
b111 7
0)
#10500
b1000 ,
b1000 %
b1000 5
b1000 ?
1)
#11000
b1000 $
b1000 6
b1000 7
0)
#11500
b1001 %
b1001 5
b1001 ?
b1001 ,
1)
#12000
b1001 $
b1001 6
b1001 7
0)
#12500
b1010 ,
b1010 %
b1010 5
b1010 ?
1)
#13000
b1010 $
b1010 6
b1010 7
0)
#13500
b1011 %
b1011 5
b1011 ?
b1011 ,
1)
#14000
b1011 $
b1011 6
b1011 7
0)
#14500
b1100 ,
b1100 %
b1100 5
b1100 ?
1)
#15000
b1100 $
b1100 6
b1100 7
0)
#15500
b1101 %
b1101 5
b1101 ?
b1101 ,
1)
#16000
b1101 $
b1101 6
b1101 7
0)
#16500
b1110 ,
b1110 %
b1110 5
b1110 ?
1)
#17000
b1110 $
b1110 6
b1110 7
0)
#17500
b1111 %
b1111 5
b1111 ?
b1111 ,
1)
#18000
b1111 $
b1111 6
b1111 7
0)
#18500
b10000 ,
b10000 %
b10000 5
b10000 ?
1)
#19000
b10000 $
b10000 6
b10000 7
0)
#19500
b10001 %
b10001 5
b10001 ?
b10001 ,
1)
#20000
b10001 $
b10001 6
b10001 7
0)
#20500
b10010 ,
b10010 %
b10010 5
b10010 ?
1)
#21000
b10010 $
b10010 6
b10010 7
0)
#21500
b10011 %
b10011 5
b10011 ?
b10011 ,
1)
#22000
b10011 $
b10011 6
b10011 7
0)
#22500
b10100 ,
b10100 %
b10100 5
b10100 ?
1)
#23000
b10100 $
b10100 6
b10100 7
0)
#23500
b10101 %
b10101 5
b10101 ?
b10101 ,
1)
#24000
b10101 $
b10101 6
b10101 7
0)
#24500
b10110 ,
b10110 %
b10110 5
b10110 ?
1)
#25000
b10110 $
b10110 6
b10110 7
0)
#25500
b10111 %
b10111 5
b10111 ?
b10111 ,
1)
#26000
b10111 $
b10111 6
b10111 7
0)
#26500
b11000 ,
b11000 %
b11000 5
b11000 ?
1)
#27000
b11000 $
b11000 6
b11000 7
0)
#27500
b11001 %
b11001 5
b11001 ?
b11001 ,
1)
#28000
b11001 $
b11001 6
b11001 7
0)
#28500
b11010 ,
b11010 %
b11010 5
b11010 ?
1)
#29000
b11010 $
b11010 6
b11010 7
0)
#29500
b11011 %
b11011 5
b11011 ?
b11011 ,
1)
#30000
b11011 $
b11011 6
b11011 7
0)
#30500
b11100 ,
b11100 %
b11100 5
b11100 ?
1)
#31000
b11100 $
b11100 6
b11100 7
0)
#31500
b11101 %
b11101 5
b11101 ?
b11011 E
b11101 ,
1)
#32000
b11101 $
b11101 6
b11101 7
0)
#32500
b11110 ,
b11100 F
b11110 %
b11110 5
b11110 ?
1)
#33000
b11110 $
b11110 6
b11110 7
0)
#33500
b11111 %
b11111 5
b11111 ?
b11111 ,
1)
#34000
b11111 $
b11111 6
b11111 7
0)
#34500
b100000 ,
b100000 %
b100000 5
b100000 ?
1)
#35000
b100000 $
b100000 6
b100000 7
0)
#35500
b100001 %
b100001 5
b100001 ?
b100001 ,
1)
#36000
b100001 $
b100001 6
b100001 7
0)
#36500
b100010 ,
b100010 %
b100010 5
b100010 ?
1)
#37000
b100010 $
b100010 6
b100010 7
0)
#37500
b100011 %
b100011 5
b100011 ?
b100011 ,
1)
#38000
b100011 $
b100011 6
b100011 7
0)
#38500
b100100 ,
b100100 %
b100100 5
b100100 ?
1)
#39000
b100100 $
b100100 6
b100100 7
0)
#39500
b11011 B
b100101 %
b100101 5
b100101 ?
b1111110 9
b100011 G
b100101 ,
1)
#40000
b100101 $
b100101 6
b100101 7
0)
#40500
b100110 ,
b100100 H
b100110 %
b100110 5
b100110 ?
1)
#41000
b100110 $
b100110 6
b100110 7
0)
#41500
b100111 %
b100111 5
b100111 ?
b100111 ,
1)
#42000
b100111 $
b100111 6
b100111 7
0)
#42500
b101000 ,
b101000 %
b101000 5
b101000 ?
1)
#43000
b101000 $
b101000 6
b101000 7
0)
#43500
b101001 %
b101001 5
b101001 ?
b101001 ,
1)
#44000
b101001 $
b101001 6
b101001 7
0)
#44500
b101010 ,
b101010 %
b101010 5
b101010 ?
1)
#45000
b101010 $
b101010 6
b101010 7
0)
#45500
b101011 %
b101011 5
b101011 ?
b101011 ,
1)
#46000
b101011 $
b101011 6
b101011 7
0)
#46500
b101100 ,
b101100 %
b101100 5
b101100 ?
1)
#47000
b101100 $
b101100 6
b101100 7
0)
#47500
b101101 %
b101101 5
b101101 ?
b101101 ,
1)
#48000
b101101 $
b101101 6
b101101 7
0)
#48500
b101110 ,
b101110 %
b101110 5
b101110 ?
1)
#49000
b101110 $
b101110 6
b101110 7
0)
#49500
b101111 %
b101111 5
b101111 ?
b101111 ,
1)
#50000
b101111 $
b101111 6
b101111 7
0)
#50500
b110000 ,
b110000 %
b110000 5
b110000 ?
1)
#51000
b110000 $
b110000 6
b110000 7
0)
#51500
b110001 %
b110001 5
b110001 ?
b110001 ,
1)
#52000
b110001 $
b110001 6
b110001 7
0)
#52500
b110010 ,
b110010 %
b110010 5
b110010 ?
1)
#53000
b110010 $
b110010 6
b110010 7
0)
#53500
b110011 %
b110011 5
b110011 ?
b110011 ,
1)
#54000
b110011 $
b110011 6
b110011 7
0)
#54500
b110100 ,
b110100 %
b110100 5
b110100 ?
1)
#55000
b110100 $
b110100 6
b110100 7
0)
#55500
b110101 %
b110101 5
b110101 ?
b110101 ,
1)
#56000
b110101 $
b110101 6
b110101 7
0)
#56500
b110110 ,
b110110 %
b110110 5
b110110 ?
1)
#57000
b110110 $
b110110 6
b110110 7
0)
#57500
b110111 %
b110111 5
b110111 ?
b110111 ,
1)
#58000
b110111 $
b110111 6
b110111 7
0)
#58500
b111000 ,
b111000 %
b111000 5
b111000 ?
1)
#59000
b111000 $
b111000 6
b111000 7
0)
#59500
b111001 %
b111001 5
b111001 ?
b111001 ,
1)
#60000
b111001 $
b111001 6
b111001 7
0)
#60500
b111010 ,
b111010 %
b111010 5
b111010 ?
1)
#61000
b111010 $
b111010 6
b111010 7
0)
#61500
b111011 %
b111011 5
b111011 ?
b111011 ,
1)
#62000
b111011 $
b111011 6
b111011 7
0)
#62500
b111100 ,
b111100 %
b111100 5
b111100 ?
1)
#63000
b111100 $
b111100 6
b111100 7
0)
#63500
b111101 %
b111101 5
b111101 ?
b111101 ,
1)
#64000
b111101 $
b111101 6
b111101 7
0)
#64500
b111110 ,
b111110 %
b111110 5
b111110 ?
1)
#65000
b111110 $
b111110 6
b111110 7
0)
#65500
b1 C
b111111 %
b111111 5
b111111 ?
b111111 ,
1)
#66000
b111111 $
b111111 6
b111111 7
0)
#66500
0"
b1000000 ,
b1 I
1)
#67000
b11 C
b1 1
1+
b0 *
b0 8
0)
#67500
1&
1"
b11 I
0#
b1000001 ,
1)
#68000
0+
0)
#68500
b1000010 ,
b1 D
1)
#69000
0)
#69500
b10 D
b1 (
b1 3
b1 =
b1 '
b1 2
b1 >
b1000011 ,
1)
#70000
0)
#70500
b1000100 ,
b10 '
b10 2
b10 >
b10 (
b10 3
b10 =
b11 D
1)
#71000
0)
#71500
b100 D
b11 (
b11 3
b11 =
b11 '
b11 2
b11 >
b1000101 ,
1)
#72000
0)
#72500
b1000110 ,
b100 '
b100 2
b100 >
b100 (
b100 3
b100 =
b101 D
1)
#73000
0)
#73500
b110 D
b101 (
b101 3
b101 =
b101 '
b101 2
b101 >
b1000111 ,
1)
#74000
0)
#74500
b1001000 ,
b110 '
b110 2
b110 >
b110 (
b110 3
b110 =
b111 D
1)
#75000
0)
#75500
b1000 D
b111 (
b111 3
b111 =
b111 '
b111 2
b111 >
b1001001 ,
1)
#76000
0)
#76500
b1001010 ,
b1000 '
b1000 2
b1000 >
b1000 (
b1000 3
b1000 =
b1001 D
1)
#77000
0)
#77500
b1010 D
b1001 (
b1001 3
b1001 =
b1001 '
b1001 2
b1001 >
b1001011 ,
1)
#78000
0)
#78500
b1001100 ,
b1010 '
b1010 2
b1010 >
b1010 (
b1010 3
b1010 =
b1011 D
1)
#79000
0)
#79500
b1100 D
b1011 (
b1011 3
b1011 =
b1011 '
b1011 2
b1011 >
b1001101 ,
1)
#80000
0)
#80500
b1001110 ,
b1100 '
b1100 2
b1100 >
b1100 (
b1100 3
b1100 =
b1101 D
1)
#81000
0)
#81500
b1110 D
b1101 (
b1101 3
b1101 =
b1101 '
b1101 2
b1101 >
b1001111 ,
1)
#82000
0)
#82500
b1010000 ,
b1110 '
b1110 2
b1110 >
b1110 (
b1110 3
b1110 =
b1111 D
1)
#83000
0)
#83500
b10000 D
b1111 (
b1111 3
b1111 =
b1111 '
b1111 2
b1111 >
b1010001 ,
1)
#84000
0)
#84500
b1010010 ,
b10000 '
b10000 2
b10000 >
b10000 (
b10000 3
b10000 =
b10001 D
1)
#85000
0)
#85500
b10010 D
b10001 (
b10001 3
b10001 =
b10001 '
b10001 2
b10001 >
b1010011 ,
1)
#86000
0)
#86500
b1010100 ,
b10010 '
b10010 2
b10010 >
b10010 (
b10010 3
b10010 =
b10011 D
1)
#87000
0)
#87500
b10100 D
b10011 (
b10011 3
b10011 =
b10011 '
b10011 2
b10011 >
b1010101 ,
1)
#88000
0)
#88500
b1010110 ,
b10100 '
b10100 2
b10100 >
b10100 (
b10100 3
b10100 =
b10101 D
1)
#89000
0)
#89500
b10110 D
b10101 (
b10101 3
b10101 =
b10101 '
b10101 2
b10101 >
b1010111 ,
1)
#90000
0)
#90500
b1011000 ,
b10110 '
b10110 2
b10110 >
b10110 (
b10110 3
b10110 =
b10111 D
1)
#91000
0)
#91500
b11000 D
b10111 (
b10111 3
b10111 =
b10111 '
b10111 2
b10111 >
b1011001 ,
1)
#92000
0)
#92500
b1011010 ,
b11000 '
b11000 2
b11000 >
b11000 (
b11000 3
b11000 =
b11001 D
1)
#93000
0)
#93500
b11010 D
b11001 (
b11001 3
b11001 =
b11001 '
b11001 2
b11001 >
b1011011 ,
1)
#94000
0)
#94500
b1011100 ,
b11010 '
b11010 2
b11010 >
b11010 (
b11010 3
b11010 =
b11011 D
1)
#95000
0)
#95500
b11100 D
b11011 (
b11011 3
b11011 =
b11011 '
b11011 2
b11011 >
b1011101 ,
1)
#96000
0)
#96500
b1011110 ,
b11100 '
b11100 2
b11100 >
b11100 (
b11100 3
b11100 =
b11101 D
1)
#97000
0)
#97500
b11110 D
b11101 (
b11101 3
b11101 =
b11101 '
b11101 2
b11101 >
b1011111 ,
1)
#98000
0)
#98500
b1100000 ,
b11110 '
b11110 2
b11110 >
b11110 (
b11110 3
b11110 =
b11111 D
1)
#99000
0)
#99500
b100000 D
b11111 (
b11111 3
b11111 =
b11111 '
b11111 2
b11111 >
b1100001 ,
1)
#100000
0)
#100500
b1100010 ,
b100000 '
b100000 2
b100000 >
b100000 (
b100000 3
b100000 =
b100001 D
1)
#101000
0)
#101500
b100010 D
b100001 (
b100001 3
b100001 =
b100001 '
b100001 2
b100001 >
b1100011 ,
1)
#102000
0)
#102500
b1100100 ,
b100010 '
b100010 2
b100010 >
b100010 (
b100010 3
b100010 =
b100011 D
1)
#103000
0)
#103500
b100100 D
b100011 (
b100011 3
b100011 =
b100011 '
b100011 2
b100011 >
b1100101 ,
1)
#104000
0)
#104500
b1100110 ,
b100100 '
b100100 2
b100100 >
b100100 (
b100100 3
b100100 =
b100101 D
1)
#105000
0)
#105500
b100110 D
b100101 (
b100101 3
b100101 =
b100101 '
b100101 2
b100101 >
b1100111 ,
1)
#106000
0)
#106500
b1101000 ,
b100110 '
b100110 2
b100110 >
b100110 (
b100110 3
b100110 =
b100111 D
1)
#107000
0)
#107500
b101000 D
b100111 (
b100111 3
b100111 =
b100111 '
b100111 2
b100111 >
b1101001 ,
1)
#108000
0)
#108500
b1101010 ,
b101000 '
b101000 2
b101000 >
b101000 (
b101000 3
b101000 =
b101001 D
1)
#109000
0)
#109500
b101010 D
b101001 (
b101001 3
b101001 =
b101001 '
b101001 2
b101001 >
b1101011 ,
1)
#110000
0)
